LICENSE
README.md
setup.py
tap_responsys/__init__.py
tap_responsys/config.py
tap_responsys/conversion.py
tap_responsys/discover.py
tap_responsys/sampling.py
tap_responsys/sftp.py
tap_responsys/sync.py
tap_responsys.egg-info/PKG-INFO
tap_responsys.egg-info/SOURCES.txt
tap_responsys.egg-info/dependency_links.txt
tap_responsys.egg-info/entry_points.txt
tap_responsys.egg-info/requires.txt
tap_responsys.egg-info/top_level.txt